nextdns_blocker/__init__.py
nextdns_blocker/__main__.py
nextdns_blocker/alias_cli.py
nextdns_blocker/analytics.py
nextdns_blocker/analytics_cli.py
nextdns_blocker/category_cli.py
nextdns_blocker/cli.py
nextdns_blocker/cli_formatter.py
nextdns_blocker/client.py
nextdns_blocker/common.py
nextdns_blocker/completion.py
nextdns_blocker/config.py
nextdns_blocker/config_cli.py
nextdns_blocker/exceptions.py
nextdns_blocker/init.py
nextdns_blocker/list_cli.py
nextdns_blocker/nextdns_cli.py
nextdns_blocker/notifications.py
nextdns_blocker/panic.py
nextdns_blocker/panic_cli.py
nextdns_blocker/pending.py
nextdns_blocker/pending_cli.py
nextdns_blocker/platform_utils.py
nextdns_blocker/protection.py
nextdns_blocker/protection_cli.py
nextdns_blocker/py.typed
nextdns_blocker/retry_queue.py
nextdns_blocker/scheduler.py
nextdns_blocker/types.py
nextdns_blocker/update_check.py
nextdns_blocker/watchdog.py
nextdns_blocker-7.1.1.dist-info/METADATA
nextdns_blocker-7.1.1.dist-info/WHEEL
nextdns_blocker-7.1.1.dist-info/entry_points.txt
nextdns_blocker-7.1.1.dist-info/licenses/LICENSE
nextdns_blocker-7.1.1.dist-info/RECORD
