Metadata-Version: 2.4
Name: nextdns-blocker
Version: 7.1.1
Summary: Automated domain blocking controller for NextDNS with per-domain scheduling
Project-URL: Homepage, https://github.com/aristeoibarra/nextdns-blocker
Project-URL: Repository, https://github.com/aristeoibarra/nextdns-blocker
Project-URL: Issues, https://github.com/aristeoibarra/nextdns-blocker/issues
Project-URL: Changelog, https://github.com/aristeoibarra/nextdns-blocker/blob/main/CHANGELOG.md
Author-email: Aristeo Ibarra <aristeo.dev@gmail.com>
License-Expression: MIT
License-File: LICENSE
Keywords: automation,blocking,dns,nextdns,parental-control,scheduling
Classifier: Development Status :: 5 - Production/Stable
Classifier: Environment :: Console
Classifier: Intended Audience :: End Users/Desktop
Classifier: Intended Audience :: System Administrators
Classifier: License :: OSI Approved :: MIT License
Classifier: Operating System :: MacOS
Classifier: Operating System :: Microsoft :: Windows
Classifier: Operating System :: POSIX :: Linux
Classifier: Programming Language :: Python :: 3
Classifier: Programming Language :: Python :: 3.9
Classifier: Programming Language :: Python :: 3.10
Classifier: Programming Language :: Python :: 3.11
Classifier: Programming Language :: Python :: 3.12
Classifier: Programming Language :: Python :: 3.13
Classifier: Topic :: Internet :: Name Service (DNS)
Classifier: Topic :: System :: Networking
Classifier: Topic :: Utilities
Requires-Python: >=3.9
Requires-Dist: click>=8.0.0
Requires-Dist: platformdirs>=3.0.0
Requires-Dist: requests<3.0.0,>=2.28.0
Requires-Dist: rich>=13.0.0
Requires-Dist: typing-extensions>=4.0.0
Requires-Dist: tzdata>=2023.3
Requires-Dist: tzlocal>=4.0
Provides-Extra: dev
Requires-Dist: bandit>=1.7.0; extra == 'dev'
Requires-Dist: black>=23.0.0; extra == 'dev'
Requires-Dist: freezegun>=1.2.0; extra == 'dev'
Requires-Dist: mypy>=1.0.0; extra == 'dev'
Requires-Dist: pytest-cov>=4.0.0; extra == 'dev'
Requires-Dist: pytest-xdist>=3.0.0; extra == 'dev'
Requires-Dist: pytest>=7.0.0; extra == 'dev'
Requires-Dist: responses>=0.23.0; extra == 'dev'
Requires-Dist: ruff>=0.1.0; extra == 'dev'
Requires-Dist: safety>=2.3.0; extra == 'dev'
Requires-Dist: types-requests>=2.28.0; extra == 'dev'
